profanity_check/__init__.py
profanity_check/data/clean_data.csv
profanity_check/data/model.joblib
profanity_check/data/vectorizer.joblib
profanity_check/profanity_check.py
profanity_check2-0.1.1.dist-info/LICENSE
profanity_check2-0.1.1.dist-info/WHEEL
profanity_check2-0.1.1.dist-info/METADATA
profanity_check2-0.1.1.dist-info/RECORD
