Metadata-Version: 2.1
Name: profanity-check2
Version: 0.1.1
Summary: Profanity Check2: Drop-in Replacement for profanity-check
Home-page: https://variancexplained.github.io/profanity-check2
License: MIT
Author: John James
Author-email: john@variancexplained.com
Requires-Python: >=3.7.1,<4.0
Classifier: Development Status :: 4 - Beta
Classifier: Intended Audience :: Developers
Classifier: License :: OSI Approved :: MIT License
Classifier: Operating System :: OS Independent
Classifier: Programming Language :: Python
Classifier: Programming Language :: Python :: 3
Classifier: Programming Language :: Python :: 3.10
Classifier: Programming Language :: Python :: 3.7
Classifier: Programming Language :: Python :: 3.8
Classifier: Programming Language :: Python :: 3.9
Classifier: Topic :: Software Development :: Libraries :: Python Modules
Classifier: Typing :: Typed
Project-URL: Documentation, https://variancexplained.github.io/profanity-check2
Project-URL: Repository, https://github.com/variancexplained/profanity-check2
